tests/__init__.py
tests/openai_test.py
tokencurator/__init__.py
tokencurator/openai.py
tokencurator-0.1.0.dist-info/METADATA
tokencurator-0.1.0.dist-info/WHEEL
tokencurator-0.1.0.dist-info/top_level.txt
tokencurator-0.1.0.dist-info/RECORD
