Metadata-Version: 2.1
Name: tokencurator
Version: 0.1.0
Summary: Manage text content to fit specific token limits of machine learning models
Home-page: https://gradecalculator.ai/
Author: Grade Calculator
Author-email: hello@gradecalculator.ai
Classifier: Development Status :: 4 - Beta
Classifier: Intended Audience :: Developers
Classifier: Programming Language :: Python :: 3
Requires-Dist: requests
Requires-Dist: tiktoken
